Metadata-Version: 2.1
Name: sphinx_design
Version: 0.4.0
Summary: A sphinx extension for designing beautiful, view size responsive web components.
Keywords: sphinx,extension,material design,web components
Author-email: Chris Sewell <chrisj_sewell@hotmail.com>
Requires-Python: >=3.7
Classifier: Development Status :: 4 - Beta
Classifier: Framework :: Sphinx :: Extension
Classifier: Intended Audience :: Developers
Classifier: License :: OSI Approved :: MIT License
Classifier: Programming Language :: Python :: 3
Classifier: Programming Language :: Python :: 3.7
Classifier: Programming Language :: Python :: 3.8
Classifier: Programming Language :: Python :: 3.9
Classifier: Programming Language :: Python :: 3.10
Classifier: Programming Language :: Python :: 3.11
Classifier: Programming Language :: Python :: Implementation :: CPython
Classifier: Topic :: Software Development :: Libraries :: Python Modules
Classifier: Topic :: Text Processing :: Markup
Classifier: Topic :: Text Processing :: Markup :: Markdown
Classifier: Topic :: Text Processing :: Markup :: reStructuredText
Requires-Dist: sphinx>=4,<7
Requires-Dist: pre-commit~=2.12 ; extra == "code_style"
Requires-Dist: myst-parser>=0.18.0,<2 ; extra == "rtd"
Requires-Dist: myst-parser>=0.18.0,<2 ; extra == "testing"
Requires-Dist: pytest~=7.1 ; extra == "testing"
Requires-Dist: pytest-cov ; extra == "testing"
Requires-Dist: pytest-regressions ; extra == "testing"
Requires-Dist: furo>=2022.06.04,<2022.07 ; extra == "theme_furo"
Requires-Dist: pydata-sphinx-theme~=0.9.0 ; extra == "theme_pydata"
Requires-Dist: sphinx-rtd-theme~=1.0 ; extra == "theme_rtd"
Requires-Dist: sphinx-book-theme~=0.3.0 ; extra == "theme_sbt"
Project-URL: Documentation, https://sphinx-design.readthedocs.io
Project-URL: Homepage, https://github.com/executablebooks/sphinx-design
Provides-Extra: code_style
Provides-Extra: rtd
Provides-Extra: testing
Provides-Extra: theme_furo
Provides-Extra: theme_pydata
Provides-Extra: theme_rtd
Provides-Extra: theme_sbt
